outbox_hitcount/__init__.py
outbox_hitcount/_version.py
outbox_hitcount/admin.py
outbox_hitcount/apps.py
outbox_hitcount/common_date.py
outbox_hitcount/hit_summary.py
outbox_hitcount/models.py
outbox_hitcount/tests.py
outbox_hitcount/views.py
outbox_hitcount/migrations/0001_initial.py
outbox_hitcount/migrations/0002_hitbrowser_version_hitdevice_version_hitos_version.py
outbox_hitcount/migrations/0003_alter_hitcount_end_date.py
outbox_hitcount/migrations/0004_alter_hitbrowser_version_alter_hitdevice_version_and_more.py
outbox_hitcount/migrations/0005_alter_hitbrowser_version_alter_hitdevice_version_and_more.py
outbox_hitcount/migrations/0006_alter_hitbrowser_version_alter_hitdevice_version_and_more.py
outbox_hitcount/migrations/0007_alter_hitbrowser_version_alter_hitdevice_version_and_more.py
outbox_hitcount/migrations/0008_remove_hitcount_browser_count_and_more.py
outbox_hitcount/migrations/0009_remove_hitlocation_name_hitlocation_city_and_more.py
outbox_hitcount/migrations/0010_hitcount_site.py
outbox_hitcount/migrations/0011_alter_hitlocation_city_alter_hitlocation_country.py
outbox_hitcount/migrations/__init__.py
django_outbox_hitcount-1.1.1.dist-info/LICENSE
django_outbox_hitcount-1.1.1.dist-info/METADATA
django_outbox_hitcount-1.1.1.dist-info/WHEEL
django_outbox_hitcount-1.1.1.dist-info/top_level.txt
django_outbox_hitcount-1.1.1.dist-info/RECORD
