Metadata-Version: 2.1
Name: django-outbox-hitcount
Version: 1.1.1
Summary: DJANGO OUTBOX HITCOUNT
Home-page: https://github.com/PROJECT-OUTBOX/django_lib_outbox_hitcount
Author-email: suratiwan03@gmail.com
Keywords: hit,count,hitcount,model base,environment,django
Classifier: License :: OSI Approved :: BSD License
Classifier: Intended Audience :: Developers
Classifier: Programming Language :: Python :: 3 :: Only
License-File: LICENSE
Requires-Dist: django-hitcount
Requires-Dist: httpagentparser
Requires-Dist: pytz
Requires-Dist: requests
